qccodar-1.0.1-py2.7-nspkg.pth
qccodar/app.py
qccodar/codarutils.py
qccodar/qcutils.py
qccodar/qcviz/qcviz.py
qccodar/qcviz/sliders.py
qccodar/test/test_qc.py
qccodar/test/test_radialshorts.py
qccodar/test/test_read.py
qccodar/test/test_write.py
qccodar-1.0.1.dist-info/DESCRIPTION.rst
qccodar-1.0.1.dist-info/METADATA
qccodar-1.0.1.dist-info/RECORD
qccodar-1.0.1.dist-info/WHEEL
qccodar-1.0.1.dist-info/entry_points.txt
qccodar-1.0.1.dist-info/metadata.json
qccodar-1.0.1.dist-info/namespace_packages.txt
qccodar-1.0.1.dist-info/top_level.txt
