Metadata-Version: 2.0
Name: qccodar
Version: 1.0.1
Summary: Apply quality controls to improve CODAR ouput
Home-page: http://nccoos.unc.edu
Author: Sara Haines
Author-email: sarahaines@unc.edu
License: GNU
Keywords: qc codar radials currents ocean science data
Platform: UNKNOWN
Classifier: Programming Language :: Python :: 2
Classifier: Programming Language :: Python :: 2.7
Requires-Dist: docopt
Requires-Dist: geopy
Requires-Dist: numpy
Provides-Extra: qcviz
Requires-Dist: matplotlib; extra == 'qcviz'
Provides-Extra: tests
Requires-Dist: nose; extra == 'tests'
